{
  "name": "robot",
  "cell": [
    12,
    18
  ],
  "source": {
    "format": "zx-fnt-9byte",
    "file": "robot.fnt",
    "bytesTotal": 866,
    "prefixBytes": 2,
    "recordBytes": 9,
    "glyphCount": 96,
    "cpBase": 32,
    "separatorNonZeroCount": 0
  },
  "glyphs": {
    "U+0020": {
      "size": [
        8,
        8
      ],
      "offset": [
        2,
        5
      ],
      "rows": [
        0,
        0,
        0,
        0,
        0,
        0,
        0,
        0
      ]
    },
    "U+0021": {
      "size": [
        8,
        8
      ],
      "offset": [
        2,
        5
      ],
      "rows": [
        0,
        56,
        56,
        56,
        56,
        0,
        56,
        56
      ]
    },
    "U+0022": {
      "size": [
        8,
        8
      ],
      "offset": [
        2,
        5
      ],
      "rows": [
        0,
        108,
        108,
        108,
        0,
        0,
        0,
        0
      ]
    },
    "U+0023": {
      "size": [
        8,
        8
      ],
      "offset": [
        2,
        5
      ],
      "rows": [
        0,
        108,
        254,
        108,
        108,
        254,
        108,
        0
      ]
    },
    "U+0024": {
      "size": [
        8,
        8
      ],
      "offset": [
        2,
        5
      ],
      "rows": [
        0,
        16,
        124,
        208,
        124,
        22,
        124,
        16
      ]
    },
    "U+0025": {
      "size": [
        8,
        8
      ],
      "offset": [
        2,
        5
      ],
      "rows": [
        0,
        198,
        206,
        28,
        56,
        112,
        230,
        198
      ]
    },
    "U+0026": {
      "size": [
        8,
        8
      ],
      "offset": [
        2,
        5
      ],
      "rows": [
        0,
        120,
        72,
        48,
        122,
        204,
        204,
        122
      ]
    },
    "U+0027": {
      "size": [
        8,
        8
      ],
      "offset": [
        2,
        5
      ],
      "rows": [
        0,
        56,
        24,
        48,
        0,
        0,
        0,
        0
      ]
    },
    "U+0028": {
      "size": [
        8,
        8
      ],
      "offset": [
        2,
        5
      ],
      "rows": [
        0,
        28,
        56,
        56,
        56,
        56,
        56,
        28
      ]
    },
    "U+0029": {
      "size": [
        8,
        8
      ],
      "offset": [
        2,
        5
      ],
      "rows": [
        0,
        112,
        56,
        56,
        56,
        56,
        56,
        112
      ]
    },
    "U+002A": {
      "size": [
        8,
        8
      ],
      "offset": [
        2,
        5
      ],
      "rows": [
        0,
        0,
        36,
        24,
        126,
        24,
        36,
        0
      ]
    },
    "U+002B": {
      "size": [
        8,
        8
      ],
      "offset": [
        2,
        5
      ],
      "rows": [
        0,
        0,
        24,
        24,
        126,
        24,
        24,
        0
      ]
    },
    "U+002C": {
      "size": [
        8,
        8
      ],
      "offset": [
        2,
        5
      ],
      "rows": [
        0,
        0,
        0,
        0,
        0,
        56,
        24,
        48
      ]
    },
    "U+002D": {
      "size": [
        8,
        8
      ],
      "offset": [
        2,
        5
      ],
      "rows": [
        0,
        0,
        0,
        0,
        126,
        126,
        0,
        0
      ]
    },
    "U+002E": {
      "size": [
        8,
        8
      ],
      "offset": [
        2,
        5
      ],
      "rows": [
        0,
        0,
        0,
        0,
        0,
        0,
        56,
        56
      ]
    },
    "U+002F": {
      "size": [
        8,
        8
      ],
      "offset": [
        2,
        5
      ],
      "rows": [
        0,
        6,
        14,
        28,
        56,
        112,
        224,
        192
      ]
    },
    "U+0030": {
      "size": [
        8,
        8
      ],
      "offset": [
        2,
        5
      ],
      "rows": [
        0,
        108,
        238,
        206,
        214,
        230,
        238,
        108
      ]
    },
    "U+0031": {
      "size": [
        8,
        8
      ],
      "offset": [
        2,
        5
      ],
      "rows": [
        0,
        24,
        120,
        56,
        56,
        56,
        56,
        56
      ]
    },
    "U+0032": {
      "size": [
        8,
        8
      ],
      "offset": [
        2,
        5
      ],
      "rows": [
        0,
        124,
        238,
        110,
        12,
        16,
        254,
        254
      ]
    },
    "U+0033": {
      "size": [
        8,
        8
      ],
      "offset": [
        2,
        5
      ],
      "rows": [
        0,
        108,
        238,
        14,
        12,
        78,
        238,
        108
      ]
    },
    "U+0034": {
      "size": [
        8,
        8
      ],
      "offset": [
        2,
        5
      ],
      "rows": [
        0,
        46,
        46,
        110,
        238,
        238,
        14,
        14
      ]
    },
    "U+0035": {
      "size": [
        8,
        8
      ],
      "offset": [
        2,
        5
      ],
      "rows": [
        0,
        254,
        224,
        204,
        14,
        110,
        238,
        108
      ]
    },
    "U+0036": {
      "size": [
        8,
        8
      ],
      "offset": [
        2,
        5
      ],
      "rows": [
        0,
        46,
        110,
        224,
        236,
        238,
        238,
        108
      ]
    },
    "U+0037": {
      "size": [
        8,
        8
      ],
      "offset": [
        2,
        5
      ],
      "rows": [
        0,
        254,
        254,
        6,
        24,
        56,
        112,
        240
      ]
    },
    "U+0038": {
      "size": [
        8,
        8
      ],
      "offset": [
        2,
        5
      ],
      "rows": [
        0,
        108,
        238,
        238,
        108,
        238,
        238,
        108
      ]
    },
    "U+0039": {
      "size": [
        8,
        8
      ],
      "offset": [
        2,
        5
      ],
      "rows": [
        0,
        108,
        238,
        238,
        110,
        14,
        236,
        232
      ]
    },
    "U+003A": {
      "size": [
        8,
        8
      ],
      "offset": [
        2,
        5
      ],
      "rows": [
        0,
        0,
        0,
        56,
        56,
        0,
        56,
        56
      ]
    },
    "U+003B": {
      "size": [
        8,
        8
      ],
      "offset": [
        2,
        5
      ],
      "rows": [
        0,
        0,
        56,
        56,
        0,
        56,
        24,
        48
      ]
    },
    "U+003C": {
      "size": [
        8,
        8
      ],
      "offset": [
        2,
        5
      ],
      "rows": [
        0,
        12,
        28,
        56,
        112,
        56,
        28,
        12
      ]
    },
    "U+003D": {
      "size": [
        8,
        8
      ],
      "offset": [
        2,
        5
      ],
      "rows": [
        0,
        0,
        254,
        254,
        0,
        254,
        254,
        0
      ]
    },
    "U+003E": {
      "size": [
        8,
        8
      ],
      "offset": [
        2,
        5
      ],
      "rows": [
        0,
        96,
        112,
        56,
        28,
        56,
        112,
        96
      ]
    },
    "U+003F": {
      "size": [
        8,
        8
      ],
      "offset": [
        2,
        5
      ],
      "rows": [
        0,
        124,
        238,
        102,
        12,
        0,
        56,
        56
      ]
    },
    "U+0040": {
      "size": [
        8,
        8
      ],
      "offset": [
        2,
        5
      ],
      "rows": [
        0,
        124,
        68,
        198,
        154,
        222,
        64,
        124
      ]
    },
    "U+0041": {
      "size": [
        8,
        8
      ],
      "offset": [
        2,
        5
      ],
      "rows": [
        0,
        124,
        238,
        238,
        254,
        238,
        238,
        238
      ]
    },
    "U+0042": {
      "size": [
        8,
        8
      ],
      "offset": [
        2,
        5
      ],
      "rows": [
        0,
        236,
        238,
        236,
        232,
        236,
        238,
        236
      ]
    },
    "U+0043": {
      "size": [
        8,
        8
      ],
      "offset": [
        2,
        5
      ],
      "rows": [
        0,
        46,
        102,
        226,
        224,
        226,
        102,
        46
      ]
    },
    "U+0044": {
      "size": [
        8,
        8
      ],
      "offset": [
        2,
        5
      ],
      "rows": [
        0,
        232,
        236,
        238,
        238,
        238,
        236,
        232
      ]
    },
    "U+0045": {
      "size": [
        8,
        8
      ],
      "offset": [
        2,
        5
      ],
      "rows": [
        0,
        238,
        230,
        224,
        236,
        224,
        230,
        238
      ]
    },
    "U+0046": {
      "size": [
        8,
        8
      ],
      "offset": [
        2,
        5
      ],
      "rows": [
        0,
        238,
        230,
        224,
        236,
        224,
        224,
        224
      ]
    },
    "U+0047": {
      "size": [
        8,
        8
      ],
      "offset": [
        2,
        5
      ],
      "rows": [
        0,
        46,
        102,
        226,
        224,
        238,
        110,
        44
      ]
    },
    "U+0048": {
      "size": [
        8,
        8
      ],
      "offset": [
        2,
        5
      ],
      "rows": [
        0,
        238,
        238,
        238,
        254,
        238,
        238,
        238
      ]
    },
    "U+0049": {
      "size": [
        8,
        8
      ],
      "offset": [
        2,
        5
      ],
      "rows": [
        0,
        56,
        56,
        56,
        56,
        56,
        56,
        56
      ]
    },
    "U+004A": {
      "size": [
        8,
        8
      ],
      "offset": [
        2,
        5
      ],
      "rows": [
        0,
        14,
        14,
        14,
        14,
        142,
        206,
        238
      ]
    },
    "U+004B": {
      "size": [
        8,
        8
      ],
      "offset": [
        2,
        5
      ],
      "rows": [
        0,
        238,
        236,
        232,
        224,
        232,
        236,
        238
      ]
    },
    "U+004C": {
      "size": [
        8,
        8
      ],
      "offset": [
        2,
        5
      ],
      "rows": [
        0,
        224,
        224,
        224,
        224,
        226,
        230,
        238
      ]
    },
    "U+004D": {
      "size": [
        8,
        8
      ],
      "offset": [
        2,
        5
      ],
      "rows": [
        0,
        198,
        238,
        254,
        238,
        238,
        238,
        238
      ]
    },
    "U+004E": {
      "size": [
        8,
        8
      ],
      "offset": [
        2,
        5
      ],
      "rows": [
        0,
        206,
        238,
        254,
        254,
        254,
        238,
        230
      ]
    },
    "U+004F": {
      "size": [
        8,
        8
      ],
      "offset": [
        2,
        5
      ],
      "rows": [
        0,
        108,
        238,
        238,
        238,
        238,
        238,
        108
      ]
    },
    "U+0050": {
      "size": [
        8,
        8
      ],
      "offset": [
        2,
        5
      ],
      "rows": [
        0,
        236,
        238,
        238,
        238,
        236,
        224,
        224
      ]
    },
    "U+0051": {
      "size": [
        8,
        8
      ],
      "offset": [
        2,
        5
      ],
      "rows": [
        0,
        108,
        238,
        238,
        238,
        238,
        238,
        110
      ]
    },
    "U+0052": {
      "size": [
        8,
        8
      ],
      "offset": [
        2,
        5
      ],
      "rows": [
        0,
        236,
        238,
        238,
        238,
        232,
        236,
        238
      ]
    },
    "U+0053": {
      "size": [
        8,
        8
      ],
      "offset": [
        2,
        5
      ],
      "rows": [
        0,
        110,
        226,
        248,
        124,
        62,
        142,
        236
      ]
    },
    "U+0054": {
      "size": [
        8,
        8
      ],
      "offset": [
        2,
        5
      ],
      "rows": [
        0,
        254,
        186,
        186,
        56,
        56,
        56,
        56
      ]
    },
    "U+0055": {
      "size": [
        8,
        8
      ],
      "offset": [
        2,
        5
      ],
      "rows": [
        0,
        238,
        238,
        238,
        238,
        238,
        238,
        108
      ]
    },
    "U+0056": {
      "size": [
        8,
        8
      ],
      "offset": [
        2,
        5
      ],
      "rows": [
        0,
        198,
        198,
        198,
        198,
        238,
        124,
        56
      ]
    },
    "U+0057": {
      "size": [
        8,
        8
      ],
      "offset": [
        2,
        5
      ],
      "rows": [
        0,
        214,
        214,
        214,
        214,
        238,
        254,
        108
      ]
    },
    "U+0058": {
      "size": [
        8,
        8
      ],
      "offset": [
        2,
        5
      ],
      "rows": [
        0,
        198,
        238,
        124,
        56,
        124,
        238,
        198
      ]
    },
    "U+0059": {
      "size": [
        8,
        8
      ],
      "offset": [
        2,
        5
      ],
      "rows": [
        0,
        238,
        238,
        238,
        124,
        56,
        56,
        56
      ]
    },
    "U+005A": {
      "size": [
        8,
        8
      ],
      "offset": [
        2,
        5
      ],
      "rows": [
        0,
        238,
        206,
        156,
        56,
        114,
        230,
        238
      ]
    },
    "U+005B": {
      "size": [
        8,
        8
      ],
      "offset": [
        2,
        5
      ],
      "rows": [
        0,
        124,
        112,
        112,
        112,
        112,
        112,
        124
      ]
    },
    "U+005C": {
      "size": [
        8,
        8
      ],
      "offset": [
        2,
        5
      ],
      "rows": [
        0,
        192,
        224,
        112,
        56,
        28,
        14,
        6
      ]
    },
    "U+005D": {
      "size": [
        8,
        8
      ],
      "offset": [
        2,
        5
      ],
      "rows": [
        0,
        124,
        28,
        28,
        28,
        28,
        28,
        124
      ]
    },
    "U+005E": {
      "size": [
        8,
        8
      ],
      "offset": [
        2,
        5
      ],
      "rows": [
        0,
        56,
        124,
        254,
        56,
        56,
        56,
        56
      ]
    },
    "U+005F": {
      "size": [
        8,
        8
      ],
      "offset": [
        2,
        5
      ],
      "rows": [
        0,
        0,
        0,
        0,
        0,
        0,
        0,
        255
      ]
    },
    "U+0060": {
      "size": [
        8,
        8
      ],
      "offset": [
        2,
        5
      ],
      "rows": [
        0,
        60,
        102,
        98,
        248,
        96,
        96,
        254
      ]
    },
    "U+0061": {
      "size": [
        8,
        8
      ],
      "offset": [
        2,
        5
      ],
      "rows": [
        0,
        0,
        120,
        12,
        108,
        236,
        236,
        108
      ]
    },
    "U+0062": {
      "size": [
        8,
        8
      ],
      "offset": [
        2,
        5
      ],
      "rows": [
        0,
        192,
        192,
        216,
        220,
        220,
        220,
        216
      ]
    },
    "U+0063": {
      "size": [
        8,
        8
      ],
      "offset": [
        2,
        5
      ],
      "rows": [
        0,
        0,
        108,
        228,
        224,
        224,
        228,
        108
      ]
    },
    "U+0064": {
      "size": [
        8,
        8
      ],
      "offset": [
        2,
        5
      ],
      "rows": [
        0,
        12,
        12,
        108,
        236,
        236,
        236,
        108
      ]
    },
    "U+0065": {
      "size": [
        8,
        8
      ],
      "offset": [
        2,
        5
      ],
      "rows": [
        0,
        0,
        88,
        220,
        220,
        192,
        220,
        88
      ]
    },
    "U+0066": {
      "size": [
        8,
        8
      ],
      "offset": [
        2,
        5
      ],
      "rows": [
        0,
        28,
        48,
        48,
        116,
        48,
        48,
        48
      ]
    },
    "U+0067": {
      "size": [
        8,
        8
      ],
      "offset": [
        2,
        5
      ],
      "rows": [
        0,
        0,
        108,
        236,
        236,
        108,
        12,
        56
      ]
    },
    "U+0068": {
      "size": [
        8,
        8
      ],
      "offset": [
        2,
        5
      ],
      "rows": [
        0,
        192,
        192,
        216,
        220,
        220,
        220,
        220
      ]
    },
    "U+0069": {
      "size": [
        8,
        8
      ],
      "offset": [
        2,
        5
      ],
      "rows": [
        0,
        0,
        56,
        0,
        56,
        56,
        56,
        56
      ]
    },
    "U+006A": {
      "size": [
        8,
        8
      ],
      "offset": [
        2,
        5
      ],
      "rows": [
        0,
        12,
        0,
        12,
        12,
        108,
        108,
        40
      ]
    },
    "U+006B": {
      "size": [
        8,
        8
      ],
      "offset": [
        2,
        5
      ],
      "rows": [
        0,
        192,
        204,
        216,
        208,
        216,
        204,
        204
      ]
    },
    "U+006C": {
      "size": [
        8,
        8
      ],
      "offset": [
        2,
        5
      ],
      "rows": [
        0,
        48,
        48,
        48,
        48,
        48,
        52,
        20
      ]
    },
    "U+006D": {
      "size": [
        8,
        8
      ],
      "offset": [
        2,
        5
      ],
      "rows": [
        0,
        0,
        212,
        214,
        214,
        214,
        214,
        214
      ]
    },
    "U+006E": {
      "size": [
        8,
        8
      ],
      "offset": [
        2,
        5
      ],
      "rows": [
        0,
        0,
        216,
        220,
        220,
        220,
        220,
        220
      ]
    },
    "U+006F": {
      "size": [
        8,
        8
      ],
      "offset": [
        2,
        5
      ],
      "rows": [
        0,
        0,
        108,
        238,
        238,
        238,
        238,
        108
      ]
    },
    "U+0070": {
      "size": [
        8,
        8
      ],
      "offset": [
        2,
        5
      ],
      "rows": [
        0,
        0,
        216,
        220,
        220,
        216,
        192,
        192
      ]
    },
    "U+0071": {
      "size": [
        8,
        8
      ],
      "offset": [
        2,
        5
      ],
      "rows": [
        0,
        0,
        108,
        236,
        236,
        108,
        12,
        12
      ]
    },
    "U+0072": {
      "size": [
        8,
        8
      ],
      "offset": [
        2,
        5
      ],
      "rows": [
        0,
        0,
        76,
        220,
        192,
        192,
        192,
        192
      ]
    },
    "U+0073": {
      "size": [
        8,
        8
      ],
      "offset": [
        2,
        5
      ],
      "rows": [
        0,
        0,
        92,
        196,
        240,
        60,
        140,
        232
      ]
    },
    "U+0074": {
      "size": [
        8,
        8
      ],
      "offset": [
        2,
        5
      ],
      "rows": [
        0,
        48,
        116,
        48,
        48,
        48,
        52,
        20
      ]
    },
    "U+0075": {
      "size": [
        8,
        8
      ],
      "offset": [
        2,
        5
      ],
      "rows": [
        0,
        0,
        238,
        238,
        238,
        238,
        238,
        108
      ]
    },
    "U+0076": {
      "size": [
        8,
        8
      ],
      "offset": [
        2,
        5
      ],
      "rows": [
        0,
        0,
        238,
        238,
        108,
        108,
        40,
        40
      ]
    },
    "U+0077": {
      "size": [
        8,
        8
      ],
      "offset": [
        2,
        5
      ],
      "rows": [
        0,
        0,
        214,
        214,
        214,
        214,
        214,
        212
      ]
    },
    "U+0078": {
      "size": [
        8,
        8
      ],
      "offset": [
        2,
        5
      ],
      "rows": [
        0,
        0,
        204,
        236,
        112,
        56,
        220,
        204
      ]
    },
    "U+0079": {
      "size": [
        8,
        8
      ],
      "offset": [
        2,
        5
      ],
      "rows": [
        0,
        0,
        236,
        236,
        236,
        108,
        12,
        120
      ]
    },
    "U+007A": {
      "size": [
        8,
        8
      ],
      "offset": [
        2,
        5
      ],
      "rows": [
        0,
        0,
        236,
        28,
        56,
        112,
        224,
        220
      ]
    },
    "U+007B": {
      "size": [
        8,
        8
      ],
      "offset": [
        2,
        5
      ],
      "rows": [
        0,
        14,
        24,
        24,
        104,
        24,
        24,
        14
      ]
    },
    "U+007C": {
      "size": [
        8,
        8
      ],
      "offset": [
        2,
        5
      ],
      "rows": [
        0,
        24,
        24,
        24,
        24,
        24,
        24,
        24
      ]
    },
    "U+007D": {
      "size": [
        8,
        8
      ],
      "offset": [
        2,
        5
      ],
      "rows": [
        0,
        112,
        24,
        24,
        22,
        24,
        24,
        112
      ]
    },
    "U+007E": {
      "size": [
        8,
        8
      ],
      "offset": [
        2,
        5
      ],
      "rows": [
        0,
        98,
        254,
        140,
        0,
        0,
        0,
        0
      ]
    },
    "U+007F": {
      "size": [
        8,
        8
      ],
      "offset": [
        2,
        5
      ],
      "rows": [
        126,
        195,
        153,
        161,
        161,
        153,
        195,
        126
      ]
    }
  }
}